en2th_transliterator/__init__.py
en2th_transliterator/cli.py
en2th_transliterator/model.py
en2th_transliterator/transliterator.py
en2th_transliterator/utils.py
en2th_transliterator-0.1.0.dist-info/LICENSE
en2th_transliterator-0.1.0.dist-info/METADATA
en2th_transliterator-0.1.0.dist-info/WHEEL
en2th_transliterator-0.1.0.dist-info/entry_points.txt
en2th_transliterator-0.1.0.dist-info/top_level.txt
en2th_transliterator-0.1.0.dist-info/RECORD
