Metadata-Version: 2.2
Name: en2th-transliterator
Version: 0.1.0
Summary: A Python package for transliterating English text to Thai using a ByT5 model
Home-page: https://github.com/tchayintr/en2th-transliterator
Author: Thodsaporn Chay-intr
Author-email: Thodsaporn Chay-intr <t.chayintr@gmail.com>
License: MIT
Project-URL: Homepage, https://github.com/tchayintr/en2th-transliterator
Project-URL: Bug Tracker, https://github.com/tchayintr/en2th-transliterator/issues
Keywords: thai,transliteration,nlp,byt5,transformers
Classifier: Programming Language :: Python :: 3
Classifier: License :: OSI Approved :: MIT License
Classifier: Operating System :: OS Independent
Classifier: Topic :: Text Processing :: Linguistic
Classifier: Intended Audience :: Developers
Classifier: Intended Audience :: Science/Research
Requires-Python: >=3.6
License-File: LICENSE
Requires-Dist: transformers>=4.0.0
Requires-Dist: torch>=1.7.0
Requires-Dist: numpy>=1.19.0
Requires-Dist: sentencepiece>=0.1.95
Requires-Dist: tqdm>=4.50.0
Dynamic: author
Dynamic: home-page
Dynamic: requires-python
